sk_client/__init__.py
sk_client/cert_utils.py
sk_client/client_acl.py
sk_client/client_auth.py
sk_client/client_base.py
sk_client/client_certs.py
sk_client/client_crypto.py
sk_client/client_intf.py
sk_client/client_ipsec.py
sk_client/client_stats.py
sk_client/client_sys.py
sk_client/client_users.py
sk_client-2.4.2.dist-info/METADATA
sk_client-2.4.2.dist-info/WHEEL
sk_client-2.4.2.dist-info/licenses/LICENSE.md
sk_client-2.4.2.dist-info/RECORD
