Metadata-Version: 2.4
Name: sk_client
Version: 2.4.2
Summary: The Secure Key REST API Client.
Project-URL: Homepage, https://jettechlabs.com/
Author-email: Jason Thomas <info@jettechlabs.com>
License: Copyright 2023, Jason Thomas. JET Technology Labs Inc.
License-File: LICENSE.md
Classifier: Environment :: Web Environment
Classifier: Intended Audience :: Developers
Classifier: Operating System :: OS Independent
Classifier: Programming Language :: Python :: 3
Classifier: Programming Language :: Python :: 3.8
Classifier: Programming Language :: Python :: 3.9
Classifier: Programming Language :: Python :: 3.10
Classifier: Programming Language :: Python :: 3.11
Classifier: Programming Language :: Python :: 3.12
Requires-Python: >=3.8
Requires-Dist: cryptography
Requires-Dist: requests
Requires-Dist: sk-schemas
